setup.cfg
setup.py
./__init__.py
./carrier.py
./carrier.xml
./sale.py
./shipment.py
./tryton.cfg
./locale/de_DE.po
./tests/__init__.py
./tests/test_carrier.py
./tests/test_views_depends.py
./view/carrier_form.xml
openlabs_carrier_pricelist.egg-info/PKG-INFO
openlabs_carrier_pricelist.egg-info/SOURCES.txt
openlabs_carrier_pricelist.egg-info/dependency_links.txt
openlabs_carrier_pricelist.egg-info/entry_points.txt
openlabs_carrier_pricelist.egg-info/not-zip-safe
openlabs_carrier_pricelist.egg-info/requires.txt
openlabs_carrier_pricelist.egg-info/top_level.txt